{
  "data_snapshot_id": "cnsvdata-2026-06-18-1768851d648a",
  "data_snapshot_hash": "1768851d648af825344ccc10c1df6ae7fbfbdd1e0017a4f1c4253bc6348ef8a6",
  "generated_at": "2026-06-19 23:38:46",
  "latest_trade_date": "2026-06-18",
  "contract_version": "1.2.0",
  "quality_status": "PASS",
  "ready_status": "PASS",
  "files": [
    {
      "path": "data/processed/trade_calendar.parquet",
      "exists": true,
      "rows": 6209,
      "columns": [
        "cal_date",
        "is_open",
        "pretrade_date",
        "exchange"
      ],
      "sha256": "95a0a6ca52f8605cfad466f95a8e782c797f19a43a7cb657ac838e11998fdf8f",
      "file_size": 63611,
      "min_trade_date": "2010-01-01",
      "max_trade_date": "2026-12-31",
      "updated_at": "2026-06-19 23:38:46",
      "source": "tushare",
      "status": "PASS"
    },
    {
      "path": "data/processed/cnsv_daily.parquet",
      "exists": true,
      "rows": 3839,
      "columns": [
        "ts_code",
        "trade_date",
        "open",
        "high",
        "low",
        "close",
        "pre_close",
        "change",
        "pct_chg",
        "vol",
        "amount",
        "source",
        "fetched_at"
      ],
      "sha256": "90cd3fc9786e9690c5160de01a567759cf295d3bf3483aaf4ff782e4a4781242",
      "file_size": 195519,
      "min_trade_date": "2010-01-04",
      "max_trade_date": "2026-06-18",
      "updated_at": "2026-06-19 23:38:46",
      "source": "tushare",
      "status": "PASS"
    },
    {
      "path": "data/processed/cnsv_1min.parquet",
      "exists": true,
      "rows": 1928,
      "columns": [
        "ts_code",
        "trade_time",
        "trade_date",
        "time",
        "open",
        "high",
        "low",
        "close",
        "vol",
        "amount",
        "source",
        "fetched_at"
      ],
      "sha256": "f287f1f3e00896fd6e825aeaf275480d0b02ad8fbbca51c9a3d56416c4790b61",
      "file_size": 59323,
      "min_trade_date": "2026-06-09",
      "max_trade_date": "2026-06-18",
      "updated_at": "2026-06-19 23:38:46",
      "source": "tushare",
      "status": "PASS"
    },
    {
      "path": "data/processed/cnsv_5min.parquet",
      "exists": true,
      "rows": 400,
      "columns": [
        "ts_code",
        "trade_time",
        "trade_date",
        "time",
        "open",
        "high",
        "low",
        "close",
        "vol",
        "amount",
        "source",
        "fetched_at"
      ],
      "sha256": "ecf980b3ceba3cd9bf3742ff2736ca940cc9358b67e7dc7219262b3a59a0eb4b",
      "file_size": 20742,
      "min_trade_date": "2026-06-09",
      "max_trade_date": "2026-06-18",
      "updated_at": "2026-06-19 23:38:46",
      "source": "tushare",
      "status": "PASS"
    },
    {
      "path": "data/processed/cnsv_15min.parquet",
      "exists": true,
      "rows": 144,
      "columns": [
        "ts_code",
        "trade_time",
        "trade_date",
        "time",
        "open",
        "high",
        "low",
        "close",
        "vol",
        "amount",
        "source",
        "fetched_at"
      ],
      "sha256": "dac053b3bc430d04cbcfabd79b3b2acf5307d132f4514889e2b853f23597c052",
      "file_size": 13095,
      "min_trade_date": "2026-06-09",
      "max_trade_date": "2026-06-18",
      "updated_at": "2026-06-19 23:38:46",
      "source": "tushare",
      "status": "PASS"
    },
    {
      "path": "data/processed/cnsv_30min.parquet",
      "exists": true,
      "rows": 80,
      "columns": [
        "ts_code",
        "trade_time",
        "trade_date",
        "time",
        "open",
        "high",
        "low",
        "close",
        "vol",
        "amount",
        "source",
        "fetched_at"
      ],
      "sha256": "427ced10dce128d4f49e42126f1c3eb420d4d625260059341ba82767a3ea7cf1",
      "file_size": 10767,
      "min_trade_date": "2026-06-09",
      "max_trade_date": "2026-06-18",
      "updated_at": "2026-06-19 23:38:46",
      "source": "tushare",
      "status": "PASS"
    },
    {
      "path": "data/processed/cnsv_60min.parquet",
      "exists": true,
      "rows": 48,
      "columns": [
        "ts_code",
        "trade_time",
        "trade_date",
        "time",
        "open",
        "high",
        "low",
        "close",
        "vol",
        "amount",
        "source",
        "fetched_at"
      ],
      "sha256": "4a0efc9a22254e65041a206af9a26dfb2806f6e269517f695d3acf565d5c9885",
      "file_size": 9464,
      "min_trade_date": "2026-06-09",
      "max_trade_date": "2026-06-18",
      "updated_at": "2026-06-19 23:38:46",
      "source": "tushare",
      "status": "PASS"
    },
    {
      "path": "data/processed/cnsv_moneyflow.parquet",
      "exists": true,
      "rows": 3839,
      "columns": [
        "ts_code",
        "trade_date",
        "buy_sm_amount",
        "sell_sm_amount",
        "buy_md_amount",
        "sell_md_amount",
        "buy_lg_amount",
        "sell_lg_amount",
        "buy_elg_amount",
        "sell_elg_amount",
        "net_mf_amount",
        "source",
        "source_version",
        "field_definition",
        "fetched_at"
      ],
      "sha256": "98188dfa6256bdebac3f292f99a543e4fd752914b318a6c0966b2fd8a5c3bcc1",
      "file_size": 277944,
      "min_trade_date": "2010-01-04",
      "max_trade_date": "2026-06-18",
      "updated_at": "2026-06-19 23:38:46",
      "source": "tushare",
      "status": "PASS"
    },
    {
      "path": "data/processed/corporate_actions.parquet",
      "exists": true,
      "rows": 1,
      "columns": [
        "ts_code",
        "event_date",
        "available_at",
        "event_type",
        "event_name",
        "description",
        "raw_source",
        "impact_level",
        "created_at"
      ],
      "sha256": "65fc3e75e6ccf7a46e9b97b542e231d4817684f0f5fc8ef973d9e8ec7ff81a24",
      "file_size": 6083,
      "min_trade_date": "2025-09-01",
      "max_trade_date": "2025-09-01",
      "updated_at": "2026-06-19 23:38:46",
      "source": "tushare",
      "status": "PASS"
    },
    {
      "path": "data/processed/structural_breaks.parquet",
      "exists": true,
      "rows": 3,
      "columns": [
        "regime_id",
        "start_date",
        "end_date",
        "description",
        "reason",
        "impact_fields",
        "model_action",
        "created_at"
      ],
      "sha256": "ad1b6aa7b2a44e8547b6278db554aece61606bc59ac5a7a57bb124f087cba7c7",
      "file_size": 5938,
      "min_trade_date": "2010-01-01",
      "max_trade_date": "2027-01-01",
      "updated_at": "2026-06-19 23:38:46",
      "source": "tushare",
      "status": "PASS"
    },
    {
      "path": "metadata/latest_trade_date.json",
      "exists": true,
      "rows": 1,
      "columns": [
        "latest_trade_date",
        "source",
        "generated_at",
        "timezone"
      ],
      "sha256": "e1636c17e3d1ca13fc14c9d9aa93ee5b5cb129f2bc867ca3ff5398271cd07bc6",
      "file_size": 135,
      "min_trade_date": null,
      "max_trade_date": null,
      "updated_at": "2026-06-19 23:38:46",
      "source": "tushare",
      "status": "PASS"
    },
    {
      "path": "metadata/next_trade_date.json",
      "exists": true,
      "rows": 1,
      "columns": [
        "current_trade_date",
        "next_trade_date",
        "source",
        "generated_at",
        "timezone"
      ],
      "sha256": "8517af915c07d39371f0c2d7711df94f7d366eedd29adfe88715c94d83fdc901",
      "file_size": 171,
      "min_trade_date": null,
      "max_trade_date": null,
      "updated_at": "2026-06-19 23:38:46",
      "source": "tushare",
      "status": "PASS"
    },
    {
      "path": "metadata/data_manifest.json",
      "exists": true,
      "rows": 1,
      "columns": [
        "snapshot_id",
        "generated_at",
        "latest_trade_date",
        "next_trade_date",
        "contract_version",
        "quality_status",
        "ready_status",
        "source",
        "files"
      ],
      "sha256": "9b0e9c26ed2a0eaa4651dcd209fe5f9c9681934d105f708e397578ffcfdc1716",
      "file_size": 8652,
      "min_trade_date": null,
      "max_trade_date": null,
      "updated_at": "2026-06-19 23:38:46",
      "source": "tushare",
      "status": "PASS"
    },
    {
      "path": "data/quality/data_quality_latest.json",
      "exists": true,
      "rows": 1,
      "columns": [
        "status",
        "generated_at",
        "failed_count",
        "warn_count",
        "checks"
      ],
      "sha256": "cd06a6d36b073894621b8854305722180ab887b03b93d288e3e88f1ce125a265",
      "file_size": 9209,
      "min_trade_date": null,
      "max_trade_date": null,
      "updated_at": "2026-06-19 23:38:46",
      "source": "tushare",
      "status": "PASS"
    }
  ]
}
