{
  "trade_date": "20260615",
  "ts_code": "600150.SH",
  "name": "中国船舶",
  "asof_time": "14:00",
  "asof_price_1400": 35.75,
  "last_valid_trade_time": "2026-06-15 14:00:00",
  "open_0930": 35.35,
  "high_until_1400": 36.43,
  "low_until_1400": 35.35,
  "close_asof_1400": 35.75,
  "vwap_until_1400": 35.858566179067964,
  "volume_until_1400": 99534856.0,
  "amount_until_1400": 3569177221.0,
  "return_from_open_to_1400": 0.011315417256011262,
  "return_from_vwap_to_1400": -0.0030276218665803434,
  "high_drawdown_until_1400": -0.018665934669228612,
  "low_rebound_until_1400": 0.011315417256011262,
  "feature_intraday_volatility_until_1400": 0.0015245142781833523,
  "feature_morning_volume_ratio": 0.8298398904600817,
  "feature_afternoon_volume_ratio": 0.17016010953991836,
  "feature_price_slope_morning": 0.0032500000000000046,
  "feature_price_slope_afternoon": -0.0018644067796610073,
  "feature_volume_slope_afternoon": -5659.881355932203,
  "minute_count_expected": 182,
  "minute_count_actual": 181,
  "missing_minute_count": 1,
  "snapshot_type": "replay",
  "replay": true,
  "created_at": "2026-06-21 12:29:30",
  "source": "intraday_1min_asof_1400"
}
