{
  "trade_date": "20251216",
  "ts_code": "600150.SH",
  "name": "中国船舶",
  "asof_time": "14:00",
  "asof_price_1400": 32.86,
  "last_valid_trade_time": "2025-12-16 14:00:00",
  "open_0930": 33.82,
  "high_until_1400": 33.82,
  "low_until_1400": 32.81,
  "close_asof_1400": 32.86,
  "vwap_until_1400": 33.07216875017813,
  "volume_until_1400": 57052242.0,
  "amount_until_1400": 1886841375.0,
  "return_from_open_to_1400": -0.028385570668243654,
  "return_from_vwap_to_1400": -0.006415326185011283,
  "high_drawdown_until_1400": -0.028385570668243654,
  "low_rebound_until_1400": 0.0015239256324290906,
  "feature_intraday_volatility_until_1400": 0.0009237235618097734,
  "feature_morning_volume_ratio": 0.8545907275650972,
  "feature_afternoon_volume_ratio": 0.14540927243490273,
  "feature_price_slope_morning": -0.008083333333333324,
  "feature_price_slope_afternoon": 0.0003389830508473902,
  "feature_volume_slope_afternoon": -3986.1525423728813,
  "minute_count_expected": 181,
  "minute_count_actual": 181,
  "missing_minute_count": 0,
  "snapshot_type": "replay",
  "replay": true,
  "created_at": "2026-06-21 13:28:03",
  "source": "intraday_1min_asof_1400"
}
